<?xml version="1.0" encoding="UTF-8"?>
<!DOCTYPE hibernate-mapping PUBLIC "-//Hibernate/Hibernate Mapping DTD 3.0//EN" "http://hibernate.sourceforge.net/hibernate-mapping-3.0.dtd">
<hibernate-mapping package="rs.fon.eklub.core.entities">
  
    <class name="Employee" table="Employee">
        <id name="id" column="idEmployee">
            <generator class="native"/>
        </id>
        <property column="nameSurname" name="nameSurname"/>
        <property column="email" name="email"/>
        <property column="address" name="address"/>
        <property column="phone" name="phone"/>
        <property column="username" name="username"/>
        <property column="password" name="password"/>
        <property column="remark" name="remark"/>
    </class> 
    
</hibernate-mapping>


